JikeAiqing/README.md
JikeAiqing/__init__.py
JikeAiqing/__main__.py
JikeAiqing/file.epub
JikeAiqing/index.html
JikeAiqing/css/__init__.py
JikeAiqing/css/annotations.css
JikeAiqing/css/main.css
JikeAiqing/css/normalize.css
JikeAiqing/css/popup.css
JikeAiqing/font/__init__.py
JikeAiqing/font/fontello.eot
JikeAiqing/font/fontello.svg
JikeAiqing/font/fontello.ttf
JikeAiqing/font/fontello.woff
JikeAiqing/img/__init__.py
JikeAiqing/img/annotator-glyph-sprite.png
JikeAiqing/img/annotator-icon-sprite.png
JikeAiqing/img/apple-touch-icon.png
JikeAiqing/img/cancelfullscreen.png
JikeAiqing/img/close.png
JikeAiqing/img/fullscreen.png
JikeAiqing/img/loader.gif
JikeAiqing/img/menu-icon.png
JikeAiqing/img/save.png
JikeAiqing/img/saved.png
JikeAiqing/img/settings-s.png
JikeAiqing/img/settings.png
JikeAiqing/img/star.png
JikeAiqing/js/__init__.py
JikeAiqing/js/epub.js
JikeAiqing/js/epub.min.js
JikeAiqing/js/epub.min.map
JikeAiqing/js/hooks.min.js
JikeAiqing/js/hooks.min.map
JikeAiqing/js/reader.js
JikeAiqing/js/reader.js.map
JikeAiqing/js/reader.min.js
JikeAiqing/js/reader.min.map
JikeAiqing/js/hooks/__init__.py
JikeAiqing/js/hooks/extensions/__init__.py
JikeAiqing/js/hooks/extensions/highlight.js
JikeAiqing/js/libs/__init__.py
JikeAiqing/js/libs/jquery.min.js
JikeAiqing/js/libs/localforage.min.js
JikeAiqing/js/libs/screenfull.js
JikeAiqing/js/libs/screenfull.min.js
JikeAiqing/js/libs/zip.min.js
JikeAiqing/js/plugins/__init__.py
JikeAiqing/js/plugins/hypothesis.js
JikeAiqing/js/plugins/search.js
jike_aiqing-2024.3.2.0.dist-info/METADATA
jike_aiqing-2024.3.2.0.dist-info/WHEEL
jike_aiqing-2024.3.2.0.dist-info/entry_points.txt
jike_aiqing-2024.3.2.0.dist-info/top_level.txt
jike_aiqing-2024.3.2.0.dist-info/RECORD
